Jenkinsfile
README.txt
setup.py
docs/HISTORY.txt
eea/__init__.py
eea.testegg.egg-info/PKG-INFO
eea.testegg.egg-info/SOURCES.txt
eea.testegg.egg-info/dependency_links.txt
eea.testegg.egg-info/entry_points.txt
eea.testegg.egg-info/namespace_packages.txt
eea.testegg.egg-info/not-zip-safe
eea.testegg.egg-info/requires.txt
eea.testegg.egg-info/top_level.txt
eea/testegg/__init__.py
eea/testegg/version.txt