Metadata-Version: 1.1
Name: eea.testegg
Version: 1.8
Summary: UNKNOWN
Home-page: http://svn.plone.org/svn/collective/
Author: UNKNOWN
Author-email: UNKNOWN
License: GPL
Platform: UNKNOWN
Classifier: Programming Language :: Python
